zep_livekit/__init__.py
zep_livekit/agent.py
zep_livekit/exceptions.py
zep_livekit-0.1.0.dist-info/METADATA
zep_livekit-0.1.0.dist-info/WHEEL
zep_livekit-0.1.0.dist-info/RECORD
