Metadata-Version: 2.4
Name: zep-livekit
Version: 0.1.0
Summary: LiveKit integration for Zep
Project-URL: Homepage, https://github.com/getzep/zep
Project-URL: Documentation, https://help.getzep.com/integrations/livekit
Project-URL: Repository, https://github.com/getzep/zep
Project-URL: Bug Tracker, https://github.com/getzep/zep/issues
Project-URL: Changelog, https://github.com/getzep/zep/blob/main/integrations/python/zep_livekit/CHANGELOG.md
Requires-Python: >=3.10
Requires-Dist: livekit-agents[openai,silero]>=1.0.0
Requires-Dist: typing-extensions>=4.0.0
Requires-Dist: zep-cloud>=3.4.3
Provides-Extra: dev
Requires-Dist: mypy>=1.0.0; extra == 'dev'
Requires-Dist: pytest-asyncio; extra == 'dev'
Requires-Dist: pytest-cov; extra == 'dev'
Requires-Dist: pytest>=7.0.0; extra == 'dev'
Requires-Dist: ruff>=0.1.0; extra == 'dev'
